nonebot_plugin_bh3_elysian_realm-0.2.0.dist-info/METADATA
nonebot_plugin_bh3_elysian_realm-0.2.0.dist-info/WHEEL
nonebot_plugin_bh3_elysian_realm-0.2.0.dist-info/licenses/LICENSE
nonebot_plugin_bh3_elysian_realm/__init__.py
nonebot_plugin_bh3_elysian_realm/config.py
nonebot_plugin_bh3_elysian_realm/plugins/__init__.py
nonebot_plugin_bh3_elysian_realm/resources/images/.gitkeep
nonebot_plugin_bh3_elysian_realm/resources/nickname.json
nonebot_plugin_bh3_elysian_realm/utils/__init__.py
nonebot_plugin_bh3_elysian_realm/utils/file_utils.py
nonebot_plugin_bh3_elysian_realm/utils/git_utils.py
nonebot_plugin_bh3_elysian_realm-0.2.0.dist-info/RECORD
