Metadata-Version: 2.1
Name: nonebot_plugin_bh3_elysian_realm
Version: 0.2.0
Summary: BH3 Elysian Realm bot power by NoneBot2
Author-Email: BalconyJH <balconyjh@gmail.com>
License: AGPL-3.0
Classifier: Development Status :: 3 - Alpha
Classifier: License :: OSI Approved :: GNU Affero General Public License v3 or later (AGPLv3+)
Classifier: Programming Language :: Python :: 3.8
Classifier: Topic :: Software Development :: Libraries :: Python Modules
Requires-Python: >=3.8.1
Requires-Dist: setuptools>=68.2.2
Requires-Dist: nonebot-adapter-onebot>=2.3.1
Requires-Dist: uvicorn[standard]>=0.23.2
Requires-Dist: fastapi>=0.104.0
Requires-Dist: nonebot2~=2.2
Requires-Dist: nonebot-plugin-send-anything-anywhere>=0.3.2
Requires-Dist: tqdm>=4.66.1
Requires-Dist: pillow>=10.1.0
Requires-Dist: nonebot-plugin-localstore>=0.5.1
Requires-Dist: nonebot-plugin-apscheduler>=0.3.0
